[
  {
    "id": "clinic01",
    "name": "Warangal OneStop Clinic",
    "pin": "2525",
    "plan": "free",
    "address": "1-8-320, Hanamkonda Chowrasta, Warangal, Telangana - 506001",
    "logo": "logos/warangalonestop.png"
  },
  {
    "id": "clinic02",
    "name": "Kakatiya Diagnostic Center",
    "pin": "2020",
    "plan": "1499",
    "address": "Opposite MGM Hospital, Subedari, Warangal - 506001",
    "logo": "logos/kakatiya.png"
  },
  {
    "id": "clinic03",
    "name": "CityCare Multispecialty Clinic",
    "pin": "2021",
    "plan": "4999",
    "address": "Street No. 3, MG Road, Hanamkonda, Warangal - 506002",
    "logo": "logos/citycare.png"
  },
  {
    "id": "clinic04",
    "name": "MedPlus Clinic",
    "pin": "3030",
    "plan": "",
    "address": "Near Bhadrakali Temple, Warangal - 506003",
    "logo": "logos/medplus.png"
  },
  {
    "id": "clinic05",
    "name": "Shree Healthcare",
    "pin": "4040",
    "plan": "",
    "address": "Ambedkar Chowk, Warangal - 506004",
    "logo": "logos/shreehealthcare.png"
  }
]
